django_searchkit-2.3.0.dist-info/licenses/LICENCE
searchkit/__init__.py
searchkit/__version__.py
searchkit/admin.py
searchkit/apps.py
searchkit/fields.py
searchkit/filters.py
searchkit/forms.py
searchkit/models.py
searchkit/tests.py
searchkit/urls.py
searchkit/utils.py
searchkit/views.py
searchkit/widgets.py
searchkit/migrations/0001_initial.py
searchkit/migrations/0002_rename_searchkitsearch_search.py
searchkit/migrations/0003_search_description.py
searchkit/migrations/__init__.py
searchkit/static/searchkit/css/searchkit.css
searchkit/static/searchkit/js/searchkit.js
searchkit/static/searchkit/js/widgets/datetime.js
searchkit/static/searchkit/js/widgets/fieldset.js
searchkit/static/searchkit/js/widgets/select2.js
searchkit/templates/admin/includes/fieldset.html
searchkit/templates/admin/searchkit/search/change_form.html
searchkit/templates/admin/searchkit/search/submit_line.html
searchkit/templates/searchkit/searchkit.html
searchkit/templates/searchkit/searchkit_buttons.html
searchkit/templates/searchkit/searchkit_filter.html
searchkit/templates/searchkit/widgets/rangewidget.html
searchkit/templatetags/__init__.py
searchkit/templatetags/searchkit.py
django_searchkit-2.3.0.dist-info/METADATA
django_searchkit-2.3.0.dist-info/WHEEL
django_searchkit-2.3.0.dist-info/top_level.txt
django_searchkit-2.3.0.dist-info/zip-safe
django_searchkit-2.3.0.dist-info/RECORD
